{"name":"Dapper-NodaTime","tagline":"Noda Time support for Dapper","body":"Dapper-NodaTime\r\n===============\r\n\r\nNoda Time support for Dapper\r\n\r\n\r\n```\r\nPM> Install-Package Dapper-NodaTime\r\n```\r\n\r\nIn your project startup sequence somewhere, call:\r\n```csharp\r\nDapperNodaTimeSetup.Register();\r\n```\r\n\r\nThat registers all of the type handlers.  Alternatively, you can register each type handler separately if you wish.\r\nFor example:\r\n```csharp\r\nSqlMapper.AddTypeHandler(LocalDateTimeHandler.Default);\r\n```\r\n\r\nWork in progress.  Currently supports the following types:\r\n\r\n- Instant\r\n- LocalDateTime\r\n- LocalDate\r\n- LocalTime\r\n- OffsetDateTime\r\n\r\n\r\nDoes not yet support:\r\n\r\n- Duration\r\n- Period\r\n- Offset\r\n- ZonedDateTime\r\n- DateTimeZone\r\n\r\nSee also:  https://github.com/StackExchange/dapper-dot-net/issues/198\r\n","google":"","note":"Don't delete this file! It's used internally to help with page regeneration."}